aiommy/__init__.py
aiommy/base.py
aiommy/dateutils.py
aiommy/db.py
aiommy/fixtures.py
aiommy/json.py
aiommy/load_dotenv.py
aiommy/logger.py
aiommy/middlewares.py
aiommy/model.py
aiommy/normalizers.py
aiommy/paginations.py
aiommy/permissions.py
aiommy/responses.py
aiommy/testing.py
aiommy/unittest.py
aiommy/views.py
aiommy/__pycache__/__init__.cpython-36.pyc
aiommy/__pycache__/dateutils.cpython-36.pyc
aiommy/__pycache__/json.cpython-36.pyc
aiommy/__pycache__/middlewares.cpython-36.pyc
aiommy/__pycache__/normalizers.cpython-36.pyc
aiommy/__pycache__/unittest.cpython-36.pyc
aiommy/__pycache__/views.cpython-36.pyc
aiommy/auth/__init__.py
aiommy/auth/coding.py
aiommy/auth/handlers.py
aiommy/auth/middlewares.py
aiommy/auth/__pycache__/__init__.cpython-36.pyc
aiommy/auth/__pycache__/coding.cpython-36.pyc
aiommy/auth/__pycache__/handlers.cpython-36.pyc
aiommy/auth/__pycache__/middlewares.cpython-36.pyc
aiommy/paginations/__init__.py
aiommy/paginations/base.py
aiommy/paginations/falling.py
aiommy/paginations/growing.py
aiommy/paginations/__pycache__/__init__.cpython-36.pyc
aiommy/paginations/__pycache__/base.cpython-36.pyc
aiommy/paginations/__pycache__/falling.cpython-36.pyc
aiommy/paginations/__pycache__/growing.cpython-36.pyc
aiommy/permissions/__init__.py
aiommy/permissions/auth.py
aiommy/permissions/base.py
aiommy/permissions/view_only.py
aiommy/permissions/__pycache__/__init__.cpython-36.pyc
aiommy/permissions/__pycache__/auth.cpython-36.pyc
aiommy/permissions/__pycache__/base.cpython-36.pyc
aiommy/permissions/__pycache__/view_only.cpython-36.pyc
aiommy-0.0.7.dist-info/DESCRIPTION.rst
aiommy-0.0.7.dist-info/METADATA
aiommy-0.0.7.dist-info/RECORD
aiommy-0.0.7.dist-info/WHEEL
aiommy-0.0.7.dist-info/metadata.json
aiommy-0.0.7.dist-info/top_level.txt
tests/__init__.py
tests/fixtures.py
tests/test_base_normalizer.py
tests/test_coding.py
tests/test_dateutils.py
tests/test_db.py
tests/test_json.py
tests/test_middlewares.py
tests/test_responses.py
tests/test_views.py
tests/__pycache__/__init__.cpython-36.pyc
tests/__pycache__/fixtures.cpython-36.pyc
tests/__pycache__/test_base_normalizer.cpython-36.pyc
