Metadata-Version: 2.0
Name: aiommy
Version: 0.0.7
Summary: A helpful tools for building web API
Home-page: https://github.com/dennypenta/aiommy
Author: Denis Dvornikov
Author-email: candyboobers@gmail.com
License: MIT
Keywords: Web API
Platform: UNKNOWN
Classifier: Development Status :: 3 - Alpha
Classifier: Intended Audience :: Developers
Classifier: Topic :: Software Development :: Libraries :: Python Modules
Classifier: License :: OSI Approved :: MIT License
Classifier: Programming Language :: Python :: 3.6
Requires-Dist: aiohttp
Requires-Dist: cerberus
Requires-Dist: pytz
Requires-Dist: peewee
Requires-Dist: peewee-async
Requires-Dist: PyJWT
Requires-Dist: psycopg2
Requires-Dist: aiopg
